setup.cfg
setup.py
pycrates/__init__.py
pycrates/crate.py
pycrates/manifest.py
pycrates/serializers.py
pycrates.egg-info/PKG-INFO
pycrates.egg-info/SOURCES.txt
pycrates.egg-info/dependency_links.txt
pycrates.egg-info/pbr.json
pycrates.egg-info/requires.txt
pycrates.egg-info/top_level.txt