Metadata-Version: 1.1
Name: pycrates
Version: 1.0beta
Summary: Easily package your object state for storage or transmission.
Home-page: https://github.com/jimmyshen/pycrates
Author: Jimmy Shen
Author-email: thejimmyshen@gmail.com
License: MIT
Download-URL: https://github.com/jimmyshen/pycrates/tarball/1.0beta
Keywords: serialization
Platform: UNKNOWN
Classifier: Development Status :: 4 - Beta
Classifier: Topic :: Software Development :: Libraries
Classifier: Programming Language :: Python :: 2.7
Classifier: License :: OSI Approved :: MIT License
